setup.cfg
setup.py
pyOpenVk/__init__.py
pyOpenVk/account.py
pyOpenVk/api.py
pyOpenVk/friends.py
pyOpenVk/groups.py
pyOpenVk/likes.py
pyOpenVk/messages.py
pyOpenVk/news_feed.py
pyOpenVk/ovk.py
pyOpenVk/polls.py
pyOpenVk/users.py
pyOpenVk/utils.py
pyOpenVk/wall.py
pyOpenVk.egg-info/PKG-INFO
pyOpenVk.egg-info/SOURCES.txt
pyOpenVk.egg-info/dependency_links.txt
pyOpenVk.egg-info/requires.txt
pyOpenVk.egg-info/top_level.txt